xplaindb_client/__init__.py
xplaindb_client/client.py
xplaindb_client-1.1.3.dist-info/licenses/LICENSE
xplaindb_client-1.1.3.dist-info/METADATA
xplaindb_client-1.1.3.dist-info/WHEEL
xplaindb_client-1.1.3.dist-info/top_level.txt
xplaindb_client-1.1.3.dist-info/RECORD
