Metadata-Version: 2.4
Name: xplaindb-client
Version: 1.1.3
Summary: Python client for XplainDB
Author: Ojas Gupta
Author-email: Ojas <gupta.ojas.27@gmail.com>
License: MIT
Classifier: Programming Language :: Python :: 3
Classifier: License :: OSI Approved :: MIT License
Classifier: Operating System :: OS Independent
Requires-Python: >=3.8
License-File: LICENSE
Requires-Dist: requests>=2.28
Dynamic: author
Dynamic: license-file
Dynamic: requires-python
